README.md
setup.cfg
setup.py
pymotion/__init__.py
pymotion/api.py
pymotion/const.py
pymotion.egg-info/PKG-INFO
pymotion.egg-info/SOURCES.txt
pymotion.egg-info/dependency_links.txt
pymotion.egg-info/requires.txt
pymotion.egg-info/top_level.txt