Metadata-Version: 2.1
Name: pymotion
Version: 0.0.0
Summary: Python API wrapper for Motion webcontrol.
Home-page: https://github.com/ludeeus/pymotion
Author: Joakim Sorensen
Author-email: ludeeus@gmail.com
License: UNKNOWN
Platform: UNKNOWN
Classifier: Programming Language :: Python :: 3
Classifier: License :: OSI Approved :: MIT License
Classifier: Operating System :: OS Independent
